tfwaves/__init__.py
tfwaves/response.py
tfwaves/stft.py
tfwaves/utils.py
tfwaves-0.1.0.dist-info/METADATA
tfwaves-0.1.0.dist-info/WHEEL
tfwaves-0.1.0.dist-info/RECORD
